org_analyze/Formatter.py
org_analyze/PageBuilder.py
org_analyze/ParserOrg.py
org_analyze/RoamDb.py
org_analyze/__init__.py
org_analyze/clocks.py
org_analyze/export_html.py
org_analyze/export_md.py
org_analyze/org2html.py
org_analyze/org2md.py
org_analyze-0.1.12.dist-info/METADATA
org_analyze-0.1.12.dist-info/WHEEL
org_analyze-0.1.12.dist-info/entry_points.txt
org_analyze-0.1.12.dist-info/top_level.txt
org_analyze-0.1.12.dist-info/RECORD
