Metadata-Version: 2.4
Name: org_analyze
Version: 0.1.12
Summary: A toolkit for extracting, analyzing, and exporting data from org-mode/org-roam notes, with support for HTML and Markdown export. See https://ojari.github.io/OrgAnalyze/ for example HTML export.
Home-page: https://github.com/ojari/OrgAnalyze
Author: Jari Ojanen
Classifier: Programming Language :: Python :: 3
Classifier: Intended Audience :: Developers
Classifier: Topic :: Text Processing :: Markup
Classifier: Topic :: Utilities
Classifier: Topic :: Text Editors :: Emacs
Requires-Python: >=3.9
Requires-Dist: pandas
Dynamic: author
Dynamic: classifier
Dynamic: description
Dynamic: description-content-type
Dynamic: home-page
Dynamic: requires-dist
Dynamic: requires-python
Dynamic: summary
